pygef/__init__.py
pygef/_version.py
pygef/bore.py
pygef/common.py
pygef/cpt.py
pygef/exceptions.py
pygef/plotting.py
pygef/py.typed
pygef/shim.py
pygef/broxml/__init__.py
pygef/broxml/mapping.py
pygef/broxml/parse_bore.py
pygef/broxml/parse_cpt.py
pygef/broxml/resolvers.py
pygef/broxml/xml_parser.py
pygef/gef/__init__.py
pygef/gef/gef.py
pygef/gef/mapping.py
pygef/gef/parse_bore.py
pygef/gef/parse_cpt.py
pygef/gef/utils.py
pygef-0.14.0.dist-info/licenses/LICENSE.txt
pygef-0.14.0.dist-info/METADATA
pygef-0.14.0.dist-info/WHEEL
pygef-0.14.0.dist-info/top_level.txt
pygef-0.14.0.dist-info/RECORD
