Metadata-Version: 2.4
Name: pygef
Version: 0.14.0
Summary: Parse soil measurument data.
License: MIT License
Project-URL: repository, https://github.com/cemsbv/pygef
Keywords: gef
Requires-Python: <3.15,>=3.11
License-File: LICENSE.txt
Requires-Dist: polars<2,>=1
Requires-Dist: lxml<7,>=5
Requires-Dist: gef-file-to-map<2,>=1
Provides-Extra: plot
Requires-Dist: matplotlib<4,>=3.6; extra == "plot"
Provides-Extra: test
Requires-Dist: coveralls<4,>=3; extra == "test"
Requires-Dist: pytest<10,>=9; extra == "test"
Provides-Extra: docs
Requires-Dist: Sphinx; extra == "docs"
Requires-Dist: sphinx-autodoc-typehints; extra == "docs"
Requires-Dist: ipython; extra == "docs"
Requires-Dist: asteroid-sphinx-theme; extra == "docs"
Requires-Dist: sphinx_rtd_theme; extra == "docs"
Provides-Extra: lint
Requires-Dist: black==25.1.0; extra == "lint"
Requires-Dist: isort==7.0.0; extra == "lint"
Provides-Extra: map
Requires-Dist: contextily<2,>=1.3.0; extra == "map"
Dynamic: license-file
